plot_regression/__init__.py
plot_regression/plot_map.py
plot_regression/results_table.py
regression_results-0.0.1.dist-info/DESCRIPTION.rst
regression_results-0.0.1.dist-info/METADATA
regression_results-0.0.1.dist-info/RECORD
regression_results-0.0.1.dist-info/WHEEL
regression_results-0.0.1.dist-info/metadata.json
regression_results-0.0.1.dist-info/top_level.txt
