Metadata-Version: 2.0
Name: regression-results
Version: 0.0.1
Summary: UNKNOWN
Home-page: https://github.com/jeffersonAsilva/Gera-o-Tech-Unimed-BH_criacao_pacotes
Author: jefferson
License: UNKNOWN
Platform: UNKNOWN
Requires-Python: >=3
Requires-Dist: Pillow (==8.4.0)
Requires-Dist: cycler (==0.11.0)
Requires-Dist: kiwisolver (==1.3.1)
Requires-Dist: matplotlib (==3.3.4)
Requires-Dist: numpy (==1.19.5)
Requires-Dist: pandas (==1.1.5)
Requires-Dist: patsy (==0.5.2)
Requires-Dist: pkg-resources (==0.0.0)
Requires-Dist: pyparsing (==3.0.9)
Requires-Dist: python-dateutil (==2.8.2)
Requires-Dist: pytz (==2022.2.1)
Requires-Dist: scipy (==1.5.4)
Requires-Dist: seaborn (==0.11.2)
Requires-Dist: six (==1.16.0)
Requires-Dist: statsmodels (==0.12.2)
